gitpathlib/__init__.py
gitpathlib/gp_base.py
gitpathlib/gp_pygit.py
gitpathlib/gp_subprocess.py
gitpathlib/testutil.py
gitpathlib/util.py
gitpathlib-0.3.dist-info/LICENSE
gitpathlib-0.3.dist-info/METADATA
gitpathlib-0.3.dist-info/WHEEL
gitpathlib-0.3.dist-info/top_level.txt
gitpathlib-0.3.dist-info/RECORD
