Metadata-Version: 2.1
Name: gitpathlib
Version: 0.3
Summary: Object-oriented paths in Git repositories
Author-email: Petr Viktorin <encukou@gmail.com>
License: MIT
Project-URL: Repository, https://github.com/encukou/gitpathlib
Keywords: git,pathlib
Classifier: Intended Audience :: Developers
Classifier: License :: OSI Approved :: MIT License
Classifier: Operating System :: POSIX :: Linux
Classifier: Programming Language :: Python
Classifier: Programming Language :: Python :: 3
Classifier: Topic :: Software Development :: Libraries
Requires-Python: >=3.9
License-File: LICENSE
Requires-Dist: pygit2 >=1.15
